py_dormakaba_dkey/__init__.py
py_dormakaba_dkey/commands.py
py_dormakaba_dkey/crypto.py
py_dormakaba_dkey/dkey.py
py_dormakaba_dkey/errors.py
py_dormakaba_dkey/models.py
py_dormakaba_dkey/py.typed
py_dormakaba_dkey-1.0.6.dist-info/LICENSE
py_dormakaba_dkey-1.0.6.dist-info/METADATA
py_dormakaba_dkey-1.0.6.dist-info/WHEEL
py_dormakaba_dkey-1.0.6.dist-info/top_level.txt
py_dormakaba_dkey-1.0.6.dist-info/zip-safe
py_dormakaba_dkey-1.0.6.dist-info/RECORD
