Metadata-Version: 2.1
Name: py-dormakaba-dkey
Version: 1.0.6
Summary: API to interact with a Dormakaba dkey lock via bluetooth
License: MIT
Project-URL: Homepage, https://github.com/emontnemery/py-dormakaba-dkey
Platform: any
Requires-Python: >=3.10.0
License-File: LICENSE
